<?xml version = '1.0' encoding = 'UTF-8'?>
<Relation class="oracle.dbtools.crest.model.design.logical.Relation" name="Relation_14" directorySegmentName="seg_0" id="5A9E7ADA-8F33-5B27-0B1B-A3A818923E7E">
<createdBy>niebieskirekin</createdBy>
<createdTime>2024-10-16 09:28:02 UTC</createdTime>
<ownerDesignName>drogowka</ownerDesignName>
<engineerTo>
<item key="DDFD5617-CD5E-8FB4-46D0-E089DBDB55C4" value="true"/>
</engineerTo>
<identifying>true</identifying>
<optionalSource>false</optionalSource>
<optionalTarget>false</optionalTarget>
<sourceCardinality>1</sourceCardinality>
<sourceEntity>CC1C1410-EC45-3366-9C65-4F8F7D642354</sourceEntity>
<targetCardinalityString>*</targetCardinalityString>
<targetEntity>D643711D-B767-FF0D-EB4C-94CF0B315894</targetEntity>
<transferable>true</transferable>
<deleteRule>NO ACTION</deleteRule>
</Relation>
