<?xml version = '1.0' encoding = 'UTF-8'?>
<FKIndexAssociation class="oracle.dbtools.crest.model.design.relational.FKIndexAssociation" directorySegmentName="seg_0" id="D0479E06-9132-3FCA-52A0-0931E308EA52" containerWithKeyObject="9B54847B-5C4B-D4EE-8791-6E59B03927A2" localFKIndex="595CC7B0-98CD-EBAB-FE98-AE3A2966FBF3" name="uczestnicy_zdarzen_zdarzenia_FK">
<sourceDDLFile>diagram-relacji.sql</sourceDDLFile>
<createdBy>niebieskirekin</createdBy>
<createdTime>2024-11-04 12:46:00 UTC</createdTime>
<ownerDesignName>drogowka1</ownerDesignName>
<importedID>FCE5D5DE-8596-246D-F6F8-97E10ABA9B7D</importedID>
<referredTableLongName>zdarzenia</referredTableLongName>
<deleteRule>NO ACTION</deleteRule>
<referredTableID>F3B0C1D5-7E02-6713-3041-7C1D8931F680</referredTableID>
<keyObject>B6C28481-73D7-4507-398C-BF59AC30F7DD</keyObject>
<referredKeyID>B6C28481-73D7-4507-398C-BF59AC30F7DD</referredKeyID>
<mandatory>false</mandatory>
<refColNames>id_zdarzenia</refColNames>
<transferable>true</transferable>
<rely>false</rely>
<columnDependencyConstraintGenerateInDDL>true</columnDependencyConstraintGenerateInDDL>
</FKIndexAssociation>